dazzle_preserve-0.7.3.dist-info/licenses/LICENSE
preserve/__init__.py
preserve/__main__.py
preserve/cli.py
preserve/config.py
preserve/output.py
preserve/paths.py
preserve/preserve.py
preserve/utils.py
preserve/version.py
preserve/handlers/__init__.py
preserve/handlers/cleanup.py
preserve/handlers/config.py
preserve/handlers/copy.py
preserve/handlers/move.py
preserve/handlers/restore.py
preserve/handlers/verify.py
preserve/help/__init__.py
preserve/help/examples.py
preservelib/__init__.py
preservelib/destination.py
preservelib/links.py
preservelib/manifest.py
preservelib/metadata.py
preservelib/operations.py
preservelib/path_warnings.py
preservelib/pathutils.py
preservelib/restore.py
preservelib/verification.py
preservelib/dazzlelink/__init__.py
preservelib/dazzlelink/core.py
dazzle_preserve-0.7.3.dist-info/METADATA
dazzle_preserve-0.7.3.dist-info/WHEEL
dazzle_preserve-0.7.3.dist-info/entry_points.txt
dazzle_preserve-0.7.3.dist-info/top_level.txt
dazzle_preserve-0.7.3.dist-info/RECORD
