Metadata-Version: 2.4
Name: dazzle-preserve
Version: 0.7.3
Summary: A tool for preserving files with path normalization and verification
Home-page: https://github.com/djdarcy/preserve
Author: Dustin Darcy
Author-email: 6962246+djdarcy@users.noreply.github.com
Classifier: Development Status :: 3 - Alpha
Classifier: Intended Audience :: Developers
Classifier: Intended Audience :: System Administrators
Classifier: License :: OSI Approved :: MIT License
Classifier: Programming Language :: Python :: 3
Classifier: Programming Language :: Python :: 3.6
Classifier: Programming Language :: Python :: 3.7
Classifier: Programming Language :: Python :: 3.8
Classifier: Programming Language :: Python :: 3.9
Classifier: Programming Language :: Python :: 3.10
Classifier: Programming Language :: Python :: 3.11
Classifier: Programming Language :: Python :: 3.12
Classifier: Programming Language :: Python :: 3.13
Classifier: Operating System :: OS Independent
Classifier: Topic :: System :: Archiving :: Backup
Classifier: Topic :: Utilities
Requires-Python: >=3.6
License-File: LICENSE
Requires-Dist: pathlib
Requires-Dist: colorama>=0.4.0
Requires-Dist: dazzle-filekit>=0.1.0
Provides-Extra: dazzlelink
Requires-Dist: dazzlelink>=0.5.0; extra == "dazzlelink"
Provides-Extra: windows
Requires-Dist: pywin32; extra == "windows"
Provides-Extra: dev
Requires-Dist: pytest; extra == "dev"
Requires-Dist: pytest-cov; extra == "dev"
Requires-Dist: black; extra == "dev"
Requires-Dist: flake8; extra == "dev"
Provides-Extra: all
Requires-Dist: dazzlelink>=0.5.0; extra == "all"
Requires-Dist: pywin32; platform_system == "Windows" and extra == "all"
Dynamic: author
Dynamic: author-email
Dynamic: classifier
Dynamic: description
Dynamic: description-content-type
Dynamic: home-page
Dynamic: license-file
Dynamic: provides-extra
Dynamic: requires-dist
Dynamic: requires-python
Dynamic: summary
